RTL Source Files/mux.v
/*
 * 4-to-1 MULTIPLEXER
 * Selects read data from active bank
 */

module mux (
    input [7:0] bank0_rdata,
    input [7:0] bank1_rdata,
    input [7:0] bank2_rdata,
    input [7:0] bank3_rdata,
    input [1:0] bank_select,
    output reg [7:0] final_rdata
);

    always @(*) begin
        case (bank_select)
            2'b00: final_rdata = bank0_rdata;
            2'b01: final_rdata = bank1_rdata;
            2'b10: final_rdata = bank2_rdata;
            2'b11: final_rdata = bank3_rdata;
            default: final_rdata = 8'h00;
        endcase
    end

endmodule

RTL Source Files/memory_bank.v
/*
 * BANK MEMORY WITH POWER FSM
 * States: ACTIVE, IDLE, SLEEP
 */

module memory_bank (
    input         clk,
    input         cs,
    input         we,
    input  [5:0]  addr,
    input  [7:0]  wdata,
    output reg [7:0] rdata
);

    // Power states
    localparam ACTIVE = 2'b00;
    localparam IDLE   = 2'b01;
    localparam SLEEP  = 2'b10;

    reg [1:0] state, next_state;
    reg [7:0] mem [0:63];
    reg [4:0] idle_count;  // 5-bit counter

    // Clock gating
    wire bank_clk = clk & (state != SLEEP);

    // FSM: State update
    always @(posedge clk) begin
        case (state)
            ACTIVE: begin
                if (!cs) begin
                    idle_count <= idle_count + 1;
                    if (idle_count > 20) next_state <= IDLE;
                end else begin
                    idle_count <= 0;
                end
            end

            IDLE: begin
                if (cs) next_state <= ACTIVE;
                else begin
                    idle_count <= idle_count + 1;
                    if (idle_count > 50) next_state <= SLEEP;
                end
            end

            SLEEP: begin
                if (cs) next_state <= ACTIVE;
            end
        endcase
    end

    always @(posedge clk) begin
        state <= next_state;
    end

    // Memory operations (clock gated)
    always @(posedge bank_clk) begin
        if (cs && we) mem[addr] <= wdata;
        if (cs && !we) rdata <= mem[addr];
    end

endmodule

RTL Source Files/decoder.v
/*
 * 2-to-4 DECODER
 * Converts 2-bit bank select to one-hot chip select
 */

module decoder (
    input [1:0] bank_select,    // 00, 01, 10, 11
    output reg [3:0] chip_select // one-hot output
);

    always @(*) begin
        case (bank_select)
            2'b00: chip_select = 4'b0001;  // Bank 0
            2'b01: chip_select = 4'b0010;  // Bank 1
            2'b10: chip_select = 4'b0100;  // Bank 2
            2'b11: chip_select = 4'b1000;  // Bank 3
            default: chip_select = 4'b0000;
        endcase
    end

endmodule

RTL Source Files/banked_memory.v
/*
 * TOP LEVEL BANKED MEMORY
 * 4 banks × 64 bytes = 256 bytes total
 */

module banked_memory (
    input clk,
    input [1:0] bank_select,
    input we,
    input [5:0] addr,
    input [7:0] wdata,
    output [7:0] rdata
);

    // Internal signals
    wire [3:0] cs;
    wire [7:0] bank0_rdata, bank1_rdata, bank2_rdata, bank3_rdata;

    // Decoder instance
    decoder u_decoder (
        .bank_select(bank_select),
        .chip_select(cs)
    );

    // Bank 0
    memory_bank u_bank0 (
        .clk(clk),
        .cs(cs[0]),
        .we(we),
        .addr(addr),
        .wdata(wdata),
        .rdata(bank0_rdata)
    );

    // Bank 1
    memory_bank u_bank1 (
        .clk(clk),
        .cs(cs[1]),
        .we(we),
        .addr(addr),
        .wdata(wdata),
        .rdata(bank1_rdata)
    );

    // Bank 2
    memory_bank u_bank2 (
        .clk(clk),
        .cs(cs[2]),
        .we(we),
        .addr(addr),
        .wdata(wdata),
        .rdata(bank2_rdata)
    );

    // Bank 3
    memory_bank u_bank3 (
        .clk(clk),
        .cs(cs[3]),
        .we(we),
        .addr(addr),
        .wdata(wdata),
        .rdata(bank3_rdata)
    );

    // Multiplexer
    mux u_mux (
        .bank0_rdata(bank0_rdata),
        .bank1_rdata(bank1_rdata),
        .bank2_rdata(bank2_rdata),
        .bank3_rdata(bank3_rdata),
        .bank_select(bank_select),
        .final_rdata(rdata)
    );

endmodule

Testbench/tb_banked_memory.v
/*
 * TESTBENCH FOR TOP LEVEL BANKED MEMORY
 */

module tb_banked_memory();

    reg clk;
    reg [1:0] bank_select;
    reg we;
    reg [5:0] addr;
    reg [7:0] wdata;
    wire [7:0] rdata;

    // Correct instantiation of banked_memory
    banked_memory uut (
        .clk(clk),
        .bank_select(bank_select),
        .we(we),
        .addr(addr),
        .wdata(wdata),
        .rdata(rdata)
    );

    // Clock generation
    initial begin
        clk = 0;
        forever #5 clk = ~clk;
    end

    // Test sequence
    initial begin
        // Dump waveforms
        $dumpfile("banked_memory.vcd");
        $dumpvars(0, tb_banked_memory);

        // Initialize
        bank_select = 0;
        we = 0;
        addr = 0;
        wdata = 0;

        #10;

        // Test 1: Write to Bank 0
        $display("Writing AA to Bank0[10]");
        bank_select = 0;
        we = 1;
        addr = 10;
        wdata = 8'hAA;
        #10 we = 0;

        // Read Bank 0
        #10;
        $display("Bank0[10] = %h", rdata);

        // Test 2: Write to Bank 2
        #20;
        $display("Writing 55 to Bank2[20]");
        bank_select = 2;
        we = 1;
        addr = 20;
        wdata = 8'h55;
        #10 we = 0;

        // Read Bank 2
        #10;
        $display("Bank2[20] = %h", rdata);

        // Test 3: Read Bank 0 (should still be AA)
        #20;
        bank_select = 0;
        addr = 10;
        #10;
        $display("Bank0[10] = %h", rdata);

        #50;
        $display("Simulation complete");
        $finish;
    end

endmodule

Waveforms/banked_memory.vcd
$date
	Sat Feb 21 03:59:06 2026
$end
$version
	Icarus Verilog
$end
$timescale
	1s
$end
$scope module tb_banked_memory $end
$var wire 8 ! rdata [7:0] $end
$var reg 6 " addr [5:0] $end
$var reg 2 # bank_select [1:0] $end
$var reg 1 $ clk $end
$var reg 8 % wdata [7:0] $end
$var reg 1 & we $end
$scope module uut $end
$var wire 6 ' addr [5:0] $end
$var wire 2 ( bank_select [1:0] $end
$var wire 1 $ clk $end
$var wire 8 ) wdata [7:0] $end
$var wire 1 & we $end
$var wire 8 * rdata [7:0] $end
$var wire 4 + cs [3:0] $end
$var wire 8 , bank3_rdata [7:0] $end
$var wire 8 - bank2_rdata [7:0] $end
$var wire 8 . bank1_rdata [7:0] $end
$var wire 8 / bank0_rdata [7:0] $end
$scope module u_bank0 $end
$var wire 6 0 addr [5:0] $end
$var wire 1 1 bank_clk $end
$var wire 1 $ clk $end
$var wire 1 2 cs $end
$var wire 8 3 wdata [7:0] $end
$var wire 1 & we $end
$var reg 5 4 idle_count [4:0] $end
$var reg 2 5 next_state [1:0] $end
$var reg 8 6 rdata [7:0] $end
$var reg 2 7 state [1:0] $end
$upscope $end
$scope module u_bank1 $end
$var wire 6 8 addr [5:0] $end
$var wire 1 9 bank_clk $end
$var wire 1 $ clk $end
$var wire 1 : cs $end
$var wire 8 ; wdata [7:0] $end
$var wire 1 & we $end
$var reg 5 < idle_count [4:0] $end
$var reg 2 = next_state [1:0] $end
$var reg 8 > rdata [7:0] $end
$var reg 2 ? state [1:0] $end
$upscope $end
$scope module u_bank2 $end
$var wire 6 @ addr [5:0] $end
$var wire 1 A bank_clk $end
$var wire 1 $ clk $end
$var wire 1 B cs $end
$var wire 8 C wdata [7:0] $end
$var wire 1 & we $end
$var reg 5 D idle_count [4:0] $end
$var reg 2 E next_state [1:0] $end
$var reg 8 F rdata [7:0] $end
$var reg 2 G state [1:0] $end
$upscope $end
$scope module u_bank3 $end
$var wire 6 H addr [5:0] $end
$var wire 1 I bank_clk $end
$var wire 1 $ clk $end
$var wire 1 J cs $end
$var wire 8 K wdata [7:0] $end
$var wire 1 & we $end
$var reg 5 L idle_count [4:0] $end
$var reg 2 M next_state [1:0] $end
$var reg 8 N rdata [7:0] $end
$var reg 2 O state [1:0] $end
$upscope $end
$scope module u_decoder $end
$var wire 2 P bank_select [1:0] $end
$var reg 4 Q chip_select [3:0] $end
$upscope $end
$scope module u_mux $end
$var wire 8 R bank0_rdata [7:0] $end
$var wire 8 S bank1_rdata [7:0] $end
$var wire 8 T bank2_rdata [7:0] $end
$var wire 8 U bank3_rdata [7:0] $end
$var wire 2 V bank_select [1:0] $end
$var reg 8 W final_rdata [7:0] $end
$upscope $end
$upscope $end
$upscope $end
$enddefinitions $end
#0
$dumpvars
bx W
b0 V
bx U
bx T
bx S
bx R
b1 Q
b0 P
bx O
bx N
bx M
bx L
b0 K
0J
0I
b0 H
bx G
bx F
bx E
bx D
b0 C
0B
0A
b0 @
bx ?
bx >
bx =
bx <
b0 ;
0:
09
b0 8
bx 7
bx 6
bx 5
bx 4
b0 3
12
01
b0 0
bx /
bx .
bx -
bx ,
b1 +
bx *
b0 )
b0 (
b0 '
0&
b0 %
0$
b0 #
b0 "
bx !
$end
#5
x1
x9
xA
xI
1$
#10
01
09
0A
0I
0$
b10101010 %
b10101010 )
b10101010 3
b10101010 ;
b10101010 C
b10101010 K
b1010 "
b1010 '
b1010 0
b1010 8
b1010 @
b1010 H
1&
#15
x1
x9
xA
xI
1$
#20
01
09
0A
0I
0$
0&
#25
b10101010 !
b10101010 *
b10101010 W
b10101010 /
b10101010 6
b10101010 R
x1
x9
xA
xI
1$
#30
01
09
0A
0I
0$
#35
x1
x9
xA
xI
1$
#40
01
09
0A
0I
0$
#45
x1
x9
xA
xI
1$
#50
1B
02
01
09
0A
0I
b100 +
b100 Q
bx !
bx *
bx W
0$
b1010101 %
b1010101 )
b1010101 3
b1010101 ;
b1010101 C
b1010101 K
b10100 "
b10100 '
b10100 0
b10100 8
b10100 @
b10100 H
1&
b10 #
b10 (
b10 P
b10 V
#55
x1
x9
xA
xI
1$
#60
01
09
0A
0I
0$
0&
#65
b1010101 !
b1010101 *
b1010101 W
b1010101 -
b1010101 F
b1010101 T
x1
x9
xA
xI
1$
#70
01
09
0A
0I
0$
#75
x1
x9
xA
xI
1$
#80
01
09
0A
0I
0$
#85
x1
x9
xA
xI
1$
#90
0B
12
01
09
0A
0I
b1 +
b1 Q
b10101010 !
b10101010 *
b10101010 W
0$
b1010 "
b1010 '
b1010 0
b1010 8
b1010 @
b1010 H
b0 #
b0 (
b0 P
b0 V
